guessit/__init__.py
guessit/__main__.py
guessit/__version__.py
guessit/api.py
guessit/jsonutils.py
guessit/monkeypatch.py
guessit/options.py
guessit/reutils.py
guessit/yamlutils.py
guessit/config/__init__.py
guessit/config/options.json
guessit/data/__init__.py
guessit/data/tlds-alpha-by-domain.txt
guessit/rules/__init__.py
guessit/rules/match_processors.py
guessit/rules/processors.py
guessit/rules/common/__init__.py
guessit/rules/common/comparators.py
guessit/rules/common/date.py
guessit/rules/common/expected.py
guessit/rules/common/formatters.py
guessit/rules/common/numeral.py
guessit/rules/common/pattern.py
guessit/rules/common/quantity.py
guessit/rules/common/validators.py
guessit/rules/common/words.py
guessit/rules/markers/__init__.py
guessit/rules/markers/groups.py
guessit/rules/markers/path.py
guessit/rules/properties/__init__.py
guessit/rules/properties/audio_codec.py
guessit/rules/properties/bit_rate.py
guessit/rules/properties/bonus.py
guessit/rules/properties/cd.py
guessit/rules/properties/container.py
guessit/rules/properties/country.py
guessit/rules/properties/crc.py
guessit/rules/properties/date.py
guessit/rules/properties/edition.py
guessit/rules/properties/episode_title.py
guessit/rules/properties/episodes.py
guessit/rules/properties/film.py
guessit/rules/properties/language.py
guessit/rules/properties/mimetype.py
guessit/rules/properties/other.py
guessit/rules/properties/part.py
guessit/rules/properties/release_group.py
guessit/rules/properties/screen_size.py
guessit/rules/properties/size.py
guessit/rules/properties/source.py
guessit/rules/properties/streaming_service.py
guessit/rules/properties/title.py
guessit/rules/properties/type.py
guessit/rules/properties/video_codec.py
guessit/rules/properties/website.py
guessit/test/__init__.py
guessit/test/enable_disable_properties.yml
guessit/test/episodes.yml
guessit/test/movies.yml
guessit/test/streaming_services.yaml
guessit/test/suggested.json
guessit/test/test-input-file.txt
guessit/test/test_api.py
guessit-3.7.0.dist-info/AUTHORS.md
guessit-3.7.0.dist-info/LICENSE
guessit-3.7.0.dist-info/METADATA
guessit-3.7.0.dist-info/WHEEL
guessit-3.7.0.dist-info/entry_points.txt
guessit-3.7.0.dist-info/top_level.txt
guessit-3.7.0.dist-info/zip-safe
guessit-3.7.0.dist-info/RECORD
