Metadata-Version: 2.1
Name: guessit
Version: 3.7.0
Summary: GuessIt - a library for guessing information from video filenames.
Home-page: https://guessit-io.github.io/guessit
Author: Rémi Alvergnat
Author-email: toilal.dev@gmail.com
License: LGPLv3
Download-URL: https://pypi.python.org/packages/source/g/guessit/guessit-3.7.0.tar.gz
Keywords: python library release parser name filename movies series episodes animes
Platform: UNKNOWN
Classifier: Development Status :: 5 - Production/Stable
Classifier: License :: OSI Approved :: GNU Lesser General Public License v3 (LGPLv3)
Classifier: Operating System :: OS Independent
Classifier: Intended Audience :: Developers
Classifier: Programming Language :: Python :: 3
Classifier: Programming Language :: Python :: 3.7
Classifier: Programming Language :: Python :: 3.8
Classifier: Programming Language :: Python :: 3.9
Classifier: Programming Language :: Python :: 3.10
Classifier: Programming Language :: Python :: 3.11
Classifier: Topic :: Multimedia
Classifier: Topic :: Software Development :: Libraries :: Python Modules
License-File: LICENSE
License-File: AUTHORS.md
Requires-Dist: rebulk (>=3.2.0)
Requires-Dist: babelfish (>=0.6.0)
Requires-Dist: python-dateutil
Requires-Dist: importlib-resources ; python_version < "3.9"
Provides-Extra: dev
Requires-Dist: tox ; extra == 'dev'
Requires-Dist: mkdocs ; extra == 'dev'
Requires-Dist: mkdocs-material ; extra == 'dev'
Requires-Dist: pyinstaller ; extra == 'dev'
Requires-Dist: python-semantic-release ; extra == 'dev'
Provides-Extra: test
Requires-Dist: pytest ; extra == 'test'
Requires-Dist: pytest-mock ; extra == 'test'
Requires-Dist: pytest-benchmark ; extra == 'test'
Requires-Dist: pytest-cov ; extra == 'test'
Requires-Dist: pylint ; extra == 'test'
Requires-Dist: PyYAML ; extra == 'test'
